cloudfiles_light.py
cloudfiles_light/__init__.py
cloudfiles_light/lib.py
cloudfiles_light/py.typed
cloudfiles_light-0.2.dist-info/LICENSE
cloudfiles_light-0.2.dist-info/METADATA
cloudfiles_light-0.2.dist-info/WHEEL
cloudfiles_light-0.2.dist-info/top_level.txt
cloudfiles_light-0.2.dist-info/RECORD
