Metadata-Version: 2.1
Name: cloudfiles-light
Version: 0.2
Summary: Lightweight helper for using rackspace cloudfiles
Home-page: https://github.com/davidszotten/cloudfiles-light
Author: David Szotten
Author-email: davidszotten@gmail.com
License: MIT
Platform: UNKNOWN
Requires-Dist: requests
Provides-Extra: dev
Requires-Dist: pytest ; extra == 'dev'
Requires-Dist: responses ; extra == 'dev'
Requires-Dist: pytest-responses ; extra == 'dev'
Requires-Dist: coverage ; extra == 'dev'
Requires-Dist: pytest-cov ; extra == 'dev'
Requires-Dist: flake8 ; extra == 'dev'
Requires-Dist: black ; extra == 'dev'
